necbaas/__init__.py
necbaas/__version__.py
necbaas/apigw.py
necbaas/buckets.py
necbaas/file_bucket.py
necbaas/group.py
necbaas/object_bucket.py
necbaas/push_sender.py
necbaas/service.py
necbaas/user.py
necbaas-7.5.1.dist-info/LICENSE
necbaas-7.5.1.dist-info/METADATA
necbaas-7.5.1.dist-info/WHEEL
necbaas-7.5.1.dist-info/top_level.txt
necbaas-7.5.1.dist-info/RECORD
